DirectoryTree.py
directory_tree_generator-0.0.1.dist-info/METADATA
directory_tree_generator-0.0.1.dist-info/WHEEL
directory_tree_generator-0.0.1.dist-info/top_level.txt
directory_tree_generator-0.0.1.dist-info/RECORD
